tail_test/__init__.py
tail_test/benchmark_generation.py
tail_test/test_llm_performance.py
tail_test/visualize.py
tail_test-0.1.2.data/scripts/tail-cli.build
tail_test-0.1.2.data/scripts/tail-cli.eval
tail_test-0.1.2.dist-info/METADATA
tail_test-0.1.2.dist-info/WHEEL
tail_test-0.1.2.dist-info/top_level.txt
tail_test-0.1.2.dist-info/RECORD
