Metadata-Version: 2.1
Name: tail-test
Version: 0.1.2
Summary: A Toolkit for automatic LLM Evaluation.
Requires-Python: >=3.8.3
Requires-Dist: openai
Requires-Dist: pandas
Requires-Dist: seaborn
Requires-Dist: tiktoken
Requires-Dist: nltk
Requires-Dist: numpy
Requires-Dist: vllm
Requires-Dist: matplotlib
